LICENSE
MANIFEST.in
README.rst
pyproject.toml
setup.cfg
setup.py
alert_winglet/__init__.py
alert_winglet/apps.py
alert_winglet/base/__init__.py
alert_winglet/base/manager.py
alert_winglet/base/sender.py
alert_winglet/discord/__init__.py
alert_winglet/discord/manager.py
alert_winglet/discord/sender.py
django_alert_winglet.egg-info/PKG-INFO
django_alert_winglet.egg-info/SOURCES.txt
django_alert_winglet.egg-info/dependency_links.txt
django_alert_winglet.egg-info/requires.txt
django_alert_winglet.egg-info/top_level.txt